{
  "timestamp": "2026-07-01T11:50:25.659132+09:00",
  "session": 3,
  "reasoning": "本セッションは最終セッション（3/3）となります。現在のポートフォリオは、現金比率が約29.7%と非常に高く、安全性が確保されています。一方で、最新ニュースではFRBの利上げ懸念やインフレの不透明感から市場が軟調であり、金（GLD）価格が急落していることが報じられています。安定志向エージェントの指針に基づき、資本の保全とインフレヘッジを両立するため、急落したゴールド（GLD）を上限20%を超えない範囲（1株）で買い増し、比率を約19.6%に調整します。また、ポートフォリオのクッション役である米国債券（BND）を15株買い増し、債券比率を補強します。これにより、株式約19.7%、債券約33.9%、ゴールド約19.6%、現金約26.7%という、極めて強固でバランスの取れたディフェンシブ・ポートフォリオが完成します。現金比率も10%以上を大きく上回る水準を維持し、手数料コストを最小限に抑えた取引を実行します。",
  "trades_executed": [
    {
      "timestamp": "2026-07-01T11:50:25.644645+09:00",
      "action": "buy",
      "ticker": "GLD",
      "qty": 1.0,
      "price": 368.38,
      "fee": 0.3684,
      "currency": "USD",
      "reason": "金価格の急落を受け、インフレヘッジおよびポートフォリオの分散効果を高めるため、1銘柄20%の上限ルールを守りつつ1株を買い増しします。",
      "status": "ok",
      "set": "a",
      "session": 3
    },
    {
      "timestamp": "2026-07-01T11:50:25.644676+09:00",
      "action": "buy",
      "ticker": "BND",
      "qty": 15.0,
      "price": 73.41,
      "fee": 1.1011,
      "currency": "USD",
      "reason": "金利上昇懸念に伴う債券価格の軟調な局面において、ポートフォリオの安定性を高めるために米国総合債券（BND）を買い増し、債券比率を補強します。",
      "status": "ok",
      "set": "a",
      "session": 3
    }
  ],
  "summary_for_report": "最終セッションに伴い、ポートフォリオの最終調整を行いました。利上げ懸念やインフレの不透明感から金価格（GLD）が急落したため、インフレヘッジとして上限20%を超えない範囲で1株買い増しました。また、ポートフォリオのクッション性を高めるため、米国債券（BND）を15株買い増しました。調整後も現金比率は約26.7%と高く、極めて強固でバランスの取れたディフェンシブな構成でシミュレーションを完了します。",
  "portfolio_value": {
    "total_usd": 48762.64,
    "total_jpy": 0,
    "breakdown": [
      {
        "ticker": "VTI",
        "qty": 26.0,
        "price": 370.04,
        "value": 9621.04,
        "currency": "USD"
      },
      {
        "ticker": "AGG",
        "qty": 98.0,
        "price": 98.98,
        "value": 9700.04,
        "currency": "USD"
      },
      {
        "ticker": "BND",
        "qty": 93.0,
        "price": 73.41,
        "value": 6827.13,
        "currency": "USD"
      },
      {
        "ticker": "GLD",
        "qty": 26.0,
        "price": 368.38,
        "value": 9577.88,
        "currency": "USD"
      }
    ],
    "cash": {
      "USD": 13036.5464,
      "JPY": 0
    }
  },
  "prices_snapshot": {
    "VTI": {
      "price": 370.04,
      "change_pct": 0.8,
      "52w_high": 374.7,
      "52w_low": 302.8,
      "currency": "USD"
    },
    "AGG": {
      "price": 98.98,
      "change_pct": -0.39,
      "52w_high": 101.46,
      "52w_low": 97.52,
      "currency": "USD"
    },
    "BND": {
      "price": 73.41,
      "change_pct": -0.41,
      "52w_high": 75.23,
      "52w_low": 72.34,
      "currency": "USD"
    },
    "GLD": {
      "price": 368.38,
      "change_pct": -0.05,
      "52w_high": 509.7,
      "52w_low": 300.96,
      "currency": "USD"
    }
  }
}