{
  "timestamp": "2026-06-08T11:56:44.061705+09:00",
  "session": 3,
  "reasoning": "本セッションは全3回中の最終セッション（3/3）です。現在のポートフォリオは、米国株式（VTI）約19.2%、米国債券（AGG/BND）約30.1%、金（GLD）約18.6%、現金約32.1%となっており、当初目標としていた安定型アセットアロケーション（株式20%、債券30%、金20%、現金30%）にほぼ完全に一致しています。インフレ懸念や金利高止まりのニュースが継続する中、これ以上の取引は0.10%の手数料コストを発生させるだけであり、資本保全の観点から不適切と判断しました。したがって、最終セッションは一切の取引を行わず、現状の最適な分散ポートフォリオを維持したままシミュレーションを完了します。",
  "trades_executed": [],
  "summary_for_report": "最終セッションにあたり、現状のポートフォリオが目標アセットアロケーション（株式20%、債券30%、金20%、現金30%）にほぼ完全に一致していることから、追加の手数料コストを避けるため取引は行わず「現状維持」としました。インフレや金利懸念が続く中、徹底した分散投資と十分な現金比率（約32%）を維持したことで、資本保全と安定したリターンを両立し、シミュレーションを極めて安全に完了しました。",
  "portfolio_value": {
    "total_usd": 49115.58,
    "total_jpy": 0,
    "breakdown": [
      {
        "ticker": "VTI",
        "qty": 26.0,
        "price": 363.38,
        "value": 9447.88,
        "currency": "USD"
      },
      {
        "ticker": "AGG",
        "qty": 100.0,
        "price": 98.17,
        "value": 9817.0,
        "currency": "USD"
      },
      {
        "ticker": "BND",
        "qty": 68.0,
        "price": 72.83,
        "value": 4952.44,
        "currency": "USD"
      },
      {
        "ticker": "GLD",
        "qty": 23.0,
        "price": 396.24,
        "value": 9113.52,
        "currency": "USD"
      }
    ],
    "cash": {
      "USD": 15784.7389,
      "JPY": 0
    }
  },
  "prices_snapshot": {
    "VTI": {
      "price": 363.38,
      "change_pct": -2.68,
      "52w_high": 374.7,
      "52w_low": 291.97,
      "currency": "USD"
    },
    "AGG": {
      "price": 98.17,
      "change_pct": -0.5,
      "52w_high": 101.46,
      "52w_low": 97.27,
      "currency": "USD"
    },
    "BND": {
      "price": 72.83,
      "change_pct": -0.45,
      "52w_high": 75.23,
      "52w_low": 72.2,
      "currency": "USD"
    },
    "GLD": {
      "price": 396.24,
      "change_pct": -3.65,
      "52w_high": 509.7,
      "52w_low": 299.89,
      "currency": "USD"
    }
  }
}